mantis_ml/__init__.py
mantis_ml/config_class.py
mantis_ml/conf/.config
mantis_ml/conf/ALS_config.yaml
mantis_ml/conf/CKD_config.yaml
mantis_ml/conf/Epilepsy_config.yaml
mantis_ml/data/README.md
mantis_ml/data/HPO/ALL_SOURCES_ALL_FREQUENCIES_genes_to_phenotype.txt
mantis_ml/data/HPO/ALL_SOURCES_FREQUENT_FEATURES_genes_to_phenotype.txt
mantis_ml/data/HPO/README.md
mantis_ml/data/HPO/process_human_phenotypes.py
mantis_ml/data/adipose_eqtl/README.md
mantis_ml/data/adipose_eqtl/adipose_eQTL.csv
mantis_ml/data/adipose_eqtl/cis_eqtl_column.txt
mantis_ml/data/adipose_eqtl/gwas_locus_column.txt
mantis_ml/data/adipose_eqtl/mmc3.xlsx
mantis_ml/data/adipose_eqtl/process_adipose_eqtl.py
mantis_ml/data/ckddb/26317775a_Hsapiens_CKD_Kidney.csv
mantis_ml/data/ckddb/26317775b_Hsapiens_CKD_Kidney.csv
mantis_ml/data/ckddb/CKDdb_annotation_features.tsv
mantis_ml/data/ensembl/hgnc_to_ens_gids.txt
mantis_ml/data/ensembl/process_hsa37_gtf.py
mantis_ml/data/essential_genes_for_mouse/README.md
mantis_ml/data/essential_genes_for_mouse/compiled_essential_mouse_features.tsv
mantis_ml/data/essential_genes_for_mouse/essential_mouse_gene_features.tsv
mantis_ml/data/essential_genes_for_mouse/essential_mouse_gene_features.tsv.tmp
mantis_ml/data/essential_genes_for_mouse/journal.pgen.1003484.s022.xls
mantis_ml/data/exSNP/CAD_eQTL_hits.csv
mantis_ml/data/exSNP/HT_eQTL_hits.csv
mantis_ml/data/exSNP/README.md
mantis_ml/data/exSNP/WTCCC_DZ_allc_allp_GSeQTL_0.05cM_list_CAD.txt
mantis_ml/data/exSNP/WTCCC_DZ_allc_allp_GSeQTL_0.05cM_list_HT.txt
mantis_ml/data/exSNP/parse_eqtl_file.py
mantis_ml/data/exac-broadinstitute/README_fordist_cleaned_exac_r03_z_data_pLI_2016_01_13.txt
mantis_ml/data/exac-broadinstitute/all_genes.tmp
mantis_ml/data/exac-broadinstitute/all_genes_exac-broad_feature_table.txt
mantis_ml/data/exac-broadinstitute/all_hgnc_genes.txt
mantis_ml/data/exac-broadinstitute/fordist_cleaned_exac_r03_march16_z_pli_rec_null_data.txt
mantis_ml/data/exac-broadinstitute/cnv/README.md
mantis_ml-1.6.5.dist-info/LICENSE
mantis_ml-1.6.5.dist-info/METADATA
mantis_ml-1.6.5.dist-info/WHEEL
mantis_ml-1.6.5.dist-info/entry_points.txt
mantis_ml-1.6.5.dist-info/top_level.txt
mantis_ml-1.6.5.dist-info/RECORD
